{
  "complexList": [
    {
      "complexNo": "111892",
      "complexName": "J노블하우스",
      "cortarNo": "1114016200",
      "realEstateTypeCode": "APT",
      "realEstateTypeName": "아파트",
      "detailAddress": "407-17",
      "latitude": 37.558812,
      "longitude": 127.00873,
      "totalHouseholdCount": 9,
      "totalBuildingCount": 1,
      "highFloor": 7,
      "lowFloor": 5,
      "useApproveYmd": "20040219",
      "dealCount": 0,
      "leaseCount": 0,
      "rentCount": 1,
      "shortTermRentCount": 0,
      "cortarAddress": "서울시 중구 신당동",
      "tourExist": false
    },
    {
      "complexNo": "120392",
      "complexName": "그린빌",
      "cortarNo": "1114016200",
      "realEstateTypeCode": "APT",
      "realEstateTypeName": "아파트",
      "detailAddress": "122-1",
      "latitude": 37.56443,
      "longitude": 127.018077,
      "totalHouseholdCount": 28,
      "totalBuildingCount": 2,
      "highFloor": 6,
      "lowFloor": 5,
      "useApproveYmd": "20031119",
      "dealCount": 0,
      "leaseCount": 0,
      "rentCount": 0,
      "shortTermRentCount": 0,
      "cortarAddress": "서울시 중구 신당동",
      "tourExist": false
    },
    {
      "complexNo": "100573",
      "complexName": "기린",
      "cortarNo": "1114016200",
      "realEstateTypeCode": "APT",
      "realEstateTypeName": "아파트",
      "detailAddress": "333-26",
      "latitude": 37.556107,
      "longitude": 127.015014,
      "totalHouseholdCount": 10,
      "totalBuildingCount": 1,
      "highFloor": 6,
      "lowFloor": 5,
      "useApproveYmd": "20040414",
      "dealCount": 0,
      "leaseCount": 0,
      "rentCount": 0,
      "shortTermRentCount": 0,
      "cortarAddress": "서울시 중구 신당동",
      "tourExist": false
    },
    {
      "complexNo": "113339",
      "complexName": "남산더힐(주상복합)",
      "cortarNo": "1114016200",
      "realEstateTypeCode": "APT",
      "realEstateTypeName": "아파트",
      "detailAddress": "420-17",
      "latitude": 37.556686,
      "longitude": 127.009913,
      "totalHouseholdCount": 32,
      "totalBuildingCount": 2,
      "highFloor": 7,
      "lowFloor": 5,
      "useApproveYmd": "20150713",
      "dealCount": 0,
      "leaseCount": 0,
      "rentCount": 0,
      "shortTermRentCount": 0,
      "cortarAddress": "서울시 중구 신당동",
      "tourExist": false
    },
    {
      "complexNo": "17543",
      "complexName": "남산정은스카이",
      "cortarNo": "1114016200",
      "realEstateTypeCode": "APT",
      "realEstateTypeName": "아파트",
      "detailAddress": "366-126",
      "latitude": 37.54919,
      "longitude": 127.007749,
      "totalHouseholdCount": 102,
      "totalBuildingCount": 1,
      "highFloor": 13,
      "lowFloor": 13,
      "useApproveYmd": "20051220",
      "dealCount": 5,
      "leaseCount": 1,
      "rentCount": 3,
      "shortTermRentCount": 0,
      "cortarAddress": "서울시 중구 신당동",
      "tourExist": false
    },
    {
      "complexNo": "3833",
      "complexName": "남산타운",
      "cortarNo": "1114016200",
      "realEstateTypeCode": "APT",
      "realEstateTypeName": "아파트",
      "detailAddress": "844",
      "latitude": 37.548907,
      "longitude": 127.008972,
      "totalHouseholdCount": 5150,
      "totalBuildingCount": 42,
      "highFloor": 18,
      "lowFloor": 11,
      "useApproveYmd": "20020525",
      "dealCount": 108,
      "leaseCount": 40,
      "rentCount": 21,
      "shortTermRentCount": 0,
      "cortarAddress": "서울시 중구 신당동",
      "tourExist": false
    },
    {
      "complexNo": "109440",
      "complexName": "남산포레스트하우스",
      "cortarNo": "1114016200",
      "realEstateTypeCode": "APT",
      "realEstateTypeName": "아파트",
      "detailAddress": "432-1666",
      "latitude": 37.54912,
      "longitude": 127.004784,
      "totalHouseholdCount": 9,
      "totalBuildingCount": 1,
      "highFloor": 6,
      "lowFloor": 1,
      "useApproveYmd": "20080722",
      "dealCount": 0,
      "leaseCount": 0,
      "rentCount": 0,
      "shortTermRentCount": 0,
      "cortarAddress": "서울시 중구 신당동",
      "tourExist": false
    },
    {
      "complexNo": "24785",
      "complexName": "남산프라임",
      "cortarNo": "1114016200",
      "realEstateTypeCode": "APT",
      "realEstateTypeName": "아파트",
      "detailAddress": "432-1632",
      "latitude": 37.54886,
      "longitude": 127.006033,
      "totalHouseholdCount": 30,
      "totalBuildingCount": 2,
      "highFloor": 5,
      "lowFloor": 5,
      "useApproveYmd": "20031013",
      "dealCount": 1,
      "leaseCount": 0,
      "rentCount": 0,
      "shortTermRentCount": 0,
      "cortarAddress": "서울시 중구 신당동",
      "tourExist": false
    },
    {
      "complexNo": "113878",
      "complexName": "노블레스2",
      "cortarNo": "1114016200",
      "realEstateTypeCode": "APT",
      "realEstateTypeName": "아파트",
      "detailAddress": "432-1653",
      "latitude": 37.549656,
      "longitude": 127.005287,
      "totalHouseholdCount": 18,
      "totalBuildingCount": 1,
      "highFloor": 5,
      "lowFloor": 4,
      "useApproveYmd": "20021218",
      "dealCount": 3,
      "leaseCount": 1,
      "rentCount": 0,
      "shortTermRentCount": 0,
      "cortarAddress": "서울시 중구 신당동",
      "tourExist": false
    },
    {
      "complexNo": "128349",
      "complexName": "노블레스하우스",
      "cortarNo": "1114016200",
      "realEstateTypeCode": "APT",
      "realEstateTypeName": "아파트",
      "detailAddress": "290-67",
      "latitude": 37.561422,
      "longitude": 127.016242,
      "totalHouseholdCount": 18,
      "totalBuildingCount": 1,
      "highFloor": 6,
      "lowFloor": 5,
      "useApproveYmd": "20070105",
      "dealCount": 2,
      "leaseCount": 0,
      "rentCount": 0,
      "shortTermRentCount": 0,
      "cortarAddress": "서울시 중구 신당동",
      "tourExist": false
    },
    {
      "complexNo": "114523",
      "complexName": "뉴그린",
      "cortarNo": "1114016200",
      "realEstateTypeCode": "APT",
      "realEstateTypeName": "아파트",
      "detailAddress": "67-129",
      "latitude": 37.562322,
      "longitude": 127.020571,
      "totalHouseholdCount": 12,
      "totalBuildingCount": 1,
      "highFloor": 6,
      "lowFloor": 3,
      "useApproveYmd": "20061106",
      "dealCount": 0,
      "leaseCount": 0,
      "rentCount": 0,
      "shortTermRentCount": 0,
      "cortarAddress": "서울시 중구 신당동",
      "tourExist": false
    },
    {
      "complexNo": "103001",
      "complexName": "다다유크레스(주상복합)",
      "cortarNo": "1114016200",
      "realEstateTypeCode": "APT",
      "realEstateTypeName": "아파트",
      "detailAddress": "372-66",
      "latitude": 37.552162,
      "longitude": 127.011897,
      "totalHouseholdCount": 12,
      "totalBuildingCount": 1,
      "highFloor": 7,
      "lowFloor": 6,
      "useApproveYmd": "20101231",
      "dealCount": 0,
      "leaseCount": 0,
      "rentCount": 0,
      "shortTermRentCount": 0,
      "cortarAddress": "서울시 중구 신당동",
      "tourExist": false
    },
    {
      "complexNo": "101741",
      "complexName": "대성드림",
      "cortarNo": "1114016200",
      "realEstateTypeCode": "APT",
      "realEstateTypeName": "아파트",
      "detailAddress": "290-52",
      "latitude": 37.561373,
      "longitude": 127.015488,
      "totalHouseholdCount": 18,
      "totalBuildingCount": 1,
      "highFloor": 6,
      "lowFloor": 6,
      "useApproveYmd": "20021210",
      "dealCount": 0,
      "leaseCount": 0,
      "rentCount": 0,
      "shortTermRentCount": 0,
      "cortarAddress": "서울시 중구 신당동",
      "tourExist": false
    },
    {
      "complexNo": "16714",
      "complexName": "동평화",
      "cortarNo": "1114016200",
      "realEstateTypeCode": "APT",
      "realEstateTypeName": "아파트",
      "detailAddress": "217-95",
      "latitude": 37.569464,
      "longitude": 127.013196,
      "totalHouseholdCount": 35,
      "totalBuildingCount": 1,
      "highFloor": 9,
      "lowFloor": 7,
      "useApproveYmd": "19681230",
      "dealCount": 0,
      "leaseCount": 0,
      "rentCount": 0,
      "shortTermRentCount": 0,
      "cortarAddress": "서울시 중구 신당동",
      "tourExist": false
    },
    {
      "complexNo": "120003",
      "complexName": "란스미어",
      "cortarNo": "1114016200",
      "realEstateTypeCode": "APT",
      "realEstateTypeName": "아파트",
      "detailAddress": "404-2",
      "latitude": 37.560143,
      "longitude": 127.011614,
      "totalHouseholdCount": 15,
      "totalBuildingCount": 1,
      "highFloor": 6,
      "lowFloor": 4,
      "useApproveYmd": "20030328",
      "dealCount": 0,
      "leaseCount": 0,
      "rentCount": 0,
      "shortTermRentCount": 0,
      "cortarAddress": "서울시 중구 신당동",
      "tourExist": false
    },
    {
      "complexNo": "27820",
      "complexName": "래미안하이베르",
      "cortarNo": "1114016200",
      "realEstateTypeCode": "APT",
      "realEstateTypeName": "아파트",
      "detailAddress": "851",
      "latitude": 37.561362,
      "longitude": 127.0228,
      "totalHouseholdCount": 784,
      "totalBuildingCount": 15,
      "highFloor": 15,
      "lowFloor": 9,
      "useApproveYmd": "20111028",
      "dealCount": 22,
      "leaseCount": 2,
      "rentCount": 3,
      "shortTermRentCount": 0,
      "cortarAddress": "서울시 중구 신당동",
      "tourExist": false
    },
    {
      "complexNo": "115971",
      "complexName": "마이스터빌",
      "cortarNo": "1114016200",
      "realEstateTypeCode": "APT",
      "realEstateTypeName": "아파트",
      "detailAddress": "407-7",
      "latitude": 37.558699,
      "longitude": 127.009082,
      "totalHouseholdCount": 14,
      "totalBuildingCount": 1,
      "highFloor": 7,
      "lowFloor": 7,
      "useApproveYmd": "20030425",
      "dealCount": 1,
      "leaseCount": 1,
      "rentCount": 1,
      "shortTermRentCount": 0,
      "cortarAddress": "서울시 중구 신당동",
      "tourExist": false
    },
    {
      "complexNo": "103352",
      "complexName": "명경",
      "cortarNo": "1114016200",
      "realEstateTypeCode": "APT",
      "realEstateTypeName": "아파트",
      "detailAddress": "432-657",
      "latitude": 37.551828,
      "longitude": 127.006457,
      "totalHouseholdCount": 15,
      "totalBuildingCount": 1,
      "highFloor": 5,
      "lowFloor": 5,
      "useApproveYmd": "20020218",
      "dealCount": 0,
      "leaseCount": 0,
      "rentCount": 0,
      "shortTermRentCount": 0,
      "cortarAddress": "서울시 중구 신당동",
      "tourExist": false
    },
    {
      "complexNo": "154261",
      "complexName": "블루채(도시형)",
      "cortarNo": "1114016200",
      "realEstateTypeCode": "APT",
      "realEstateTypeName": "아파트",
      "detailAddress": "236-56",
      "latitude": 37.562456,
      "longitude": 127.01266,
      "totalHouseholdCount": 10,
      "totalBuildingCount": 1,
      "highFloor": 5,
      "lowFloor": 5,
      "useApproveYmd": "20220228",
      "dealCount": 0,
      "leaseCount": 0,
      "rentCount": 0,
      "shortTermRentCount": 0,
      "cortarAddress": "서울시 중구 신당동",
      "tourExist": false
    },
    {
      "complexNo": "26796",
      "complexName": "삼성V",
      "cortarNo": "1114016200",
      "realEstateTypeCode": "APT",
      "realEstateTypeName": "아파트",
      "detailAddress": "290-42",
      "latitude": 37.561477,
      "longitude": 127.015962,
      "totalHouseholdCount": 30,
      "totalBuildingCount": 2,
      "highFloor": 6,
      "lowFloor": 6,
      "useApproveYmd": "20070425",
      "dealCount": 1,
      "leaseCount": 0,
      "rentCount": 0,
      "shortTermRentCount": 0,
      "cortarAddress": "서울시 중구 신당동",
      "tourExist": false
    },
    {
      "complexNo": "18301",
      "complexName": "삼성홈타운신당",
      "cortarNo": "1114016200",
      "realEstateTypeCode": "APT",
      "realEstateTypeName": "아파트",
      "detailAddress": "849",
      "latitude": 37.562809,
      "longitude": 127.016906,
      "totalHouseholdCount": 63,
      "totalBuildingCount": 1,
      "highFloor": 13,
      "lowFloor": 6,
      "useApproveYmd": "20040419",
      "dealCount": 2,
      "leaseCount": 0,
      "rentCount": 0,
      "shortTermRentCount": 0,
      "cortarAddress": "서울시 중구 신당동",
      "tourExist": false
    },
    {
      "complexNo": "26602",
      "complexName": "성지",
      "cortarNo": "1114016200",
      "realEstateTypeCode": "APT",
      "realEstateTypeName": "아파트",
      "detailAddress": "333-9",
      "latitude": 37.556215,
      "longitude": 127.01388,
      "totalHouseholdCount": 18,
      "totalBuildingCount": 1,
      "highFloor": 5,
      "lowFloor": 3,
      "useApproveYmd": "20020911",
      "dealCount": 0,
      "leaseCount": 0,
      "rentCount": 0,
      "shortTermRentCount": 0,
      "cortarAddress": "서울시 중구 신당동",
      "tourExist": false
    },
    {
      "complexNo": "124250",
      "complexName": "신당(도시형)",
      "cortarNo": "1114016200",
      "realEstateTypeCode": "APT",
      "realEstateTypeName": "아파트",
      "detailAddress": "165-39",
      "latitude": 37.562748,
      "longitude": 127.022668,
      "totalHouseholdCount": 19,
      "totalBuildingCount": 1,
      "highFloor": 5,
      "lowFloor": 4,
      "useApproveYmd": "20130425",
      "dealCount": 0,
      "leaseCount": 0,
      "rentCount": 0,
      "shortTermRentCount": 0,
      "cortarAddress": "서울시 중구 신당동",
      "tourExist": false
    },
    {
      "complexNo": "115966",
      "complexName": "신당KCC스위첸",
      "cortarNo": "1114016200",
      "realEstateTypeCode": "APT",
      "realEstateTypeName": "아파트",
      "detailAddress": "856",
      "latitude": 37.56327,
      "longitude": 127.025513,
      "totalHouseholdCount": 176,
      "totalBuildingCount": 3,
      "highFloor": 16,
      "lowFloor": 9,
      "useApproveYmd": "20190605",
      "dealCount": 13,
      "leaseCount": 0,
      "rentCount": 3,
      "shortTermRentCount": 0,
      "cortarAddress": "서울시 중구 신당동",
      "tourExist": false
    },
    {
      "complexNo": "172477",
      "complexName": "신당빌라트",
      "cortarNo": "1114016200",
      "realEstateTypeCode": "APT",
      "realEstateTypeName": "아파트",
      "detailAddress": "432-1669",
      "latitude": 37.548735,
      "longitude": 127.005366,
      "totalHouseholdCount": 9,
      "totalBuildingCount": 1,
      "highFloor": 5,
      "lowFloor": 4,
      "useApproveYmd": "20030626",
      "dealCount": 0,
      "leaseCount": 0,
      "rentCount": 0,
      "shortTermRentCount": 0,
      "cortarAddress": "서울시 중구 신당동",
      "tourExist": false
    },
    {
      "complexNo": "1237",
      "complexName": "신당삼성",
      "cortarNo": "1114016200",
      "realEstateTypeCode": "APT",
      "realEstateTypeName": "아파트",
      "detailAddress": "843",
      "latitude": 37.558928,
      "longitude": 127.017992,
      "totalHouseholdCount": 994,
      "totalBuildingCount": 14,
      "highFloor": 23,
      "lowFloor": 14,
      "useApproveYmd": "19991222",
      "dealCount": 31,
      "leaseCount": 5,
      "rentCount": 3,
      "shortTermRentCount": 0,
      "cortarAddress": "서울시 중구 신당동",
      "tourExist": false
    },
    {
      "complexNo": "105139",
      "complexName": "신당아르브(도시형)",
      "cortarNo": "1114016200",
      "realEstateTypeCode": "APT",
      "realEstateTypeName": "아파트",
      "detailAddress": "160-5",
      "latitude": 37.564979,
      "longitude": 127.023296,
      "totalHouseholdCount": 60,
      "totalBuildingCount": 1,
      "highFloor": 17,
      "lowFloor": 7,
      "useApproveYmd": "20140919",
      "dealCount": 4,
      "leaseCount": 1,
      "rentCount": 0,
      "shortTermRentCount": 0,
      "cortarAddress": "서울시 중구 신당동",
      "tourExist": false
    },
    {
      "complexNo": "110696",
      "complexName": "신당역솔하임5차(도시형)",
      "cortarNo": "1114016200",
      "realEstateTypeCode": "APT",
      "realEstateTypeName": "아파트",
      "detailAddress": "140-23",
      "latitude": 37.565386,
      "longitude": 127.021219,
      "totalHouseholdCount": 49,
      "totalBuildingCount": 1,
      "highFloor": 20,
      "lowFloor": 20,
      "useApproveYmd": "20160224",
      "dealCount": 1,
      "leaseCount": 0,
      "rentCount": 0,
      "shortTermRentCount": 0,
      "cortarAddress": "서울시 중구 신당동",
      "tourExist": false
    },
    {
      "complexNo": "9931",
      "complexName": "신당파라다이스",
      "cortarNo": "1114016200",
      "realEstateTypeCode": "APT",
      "realEstateTypeName": "아파트",
      "detailAddress": "846",
      "latitude": 37.56247,
      "longitude": 127.017307,
      "totalHouseholdCount": 132,
      "totalBuildingCount": 1,
      "highFloor": 15,
      "lowFloor": 6,
      "useApproveYmd": "20000710",
      "dealCount": 2,
      "leaseCount": 0,
      "rentCount": 0,
      "shortTermRentCount": 0,
      "cortarAddress": "서울시 중구 신당동",
      "tourExist": false
    },
    {
      "complexNo": "137485",
      "complexName": "신당파인힐하나유보라(민간임대)",
      "cortarNo": "1114016200",
      "realEstateTypeCode": "APT",
      "realEstateTypeName": "아파트",
      "detailAddress": "855",
      "latitude": 37.564617,
      "longitude": 127.024659,
      "totalHouseholdCount": 718,
      "totalBuildingCount": 6,
      "highFloor": 20,
      "lowFloor": 11,
      "useApproveYmd": "20190607",
      "dealCount": 0,
      "leaseCount": 0,
      "rentCount": 0,
      "shortTermRentCount": 0,
      "cortarAddress": "서울시 중구 신당동",
      "tourExist": false
    },
    {
      "complexNo": "13845",
      "complexName": "신당푸르지오",
      "cortarNo": "1114016200",
      "realEstateTypeCode": "APT",
      "realEstateTypeName": "아파트",
      "detailAddress": "850",
      "latitude": 37.559263,
      "longitude": 127.01959,
      "totalHouseholdCount": 461,
      "totalBuildingCount": 9,
      "highFloor": 23,
      "lowFloor": 6,
      "useApproveYmd": "20051228",
      "dealCount": 24,
      "leaseCount": 0,
      "rentCount": 1,
      "shortTermRentCount": 0,
      "cortarAddress": "서울시 중구 신당동",
      "tourExist": false
    },
    {
      "complexNo": "26547",
      "complexName": "신신",
      "cortarNo": "1114016200",
      "realEstateTypeCode": "APT",
      "realEstateTypeName": "아파트",
      "detailAddress": "432-1957",
      "latitude": 37.550997,
      "longitude": 127.005212,
      "totalHouseholdCount": 18,
      "totalBuildingCount": 1,
      "highFloor": 5,
      "lowFloor": 5,
      "useApproveYmd": "20011123",
      "dealCount": 0,
      "leaseCount": 0,
      "rentCount": 0,
      "shortTermRentCount": 0,
      "cortarAddress": "서울시 중구 신당동",
      "tourExist": false
    },
    {
      "complexNo": "11177",
      "complexName": "약수",
      "cortarNo": "1114016200",
      "realEstateTypeCode": "APT",
      "realEstateTypeName": "아파트",
      "detailAddress": "372-13",
      "latitude": 37.553829,
      "longitude": 127.010845,
      "totalHouseholdCount": 44,
      "totalBuildingCount": 1,
      "highFloor": 5,
      "lowFloor": 5,
      "useApproveYmd": "19680904",
      "dealCount": 3,
      "leaseCount": 0,
      "rentCount": 1,
      "shortTermRentCount": 0,
      "cortarAddress": "서울시 중구 신당동",
      "tourExist": false
    },
    {
      "complexNo": "11718",
      "complexName": "약수넥스빌",
      "cortarNo": "1114016200",
      "realEstateTypeCode": "APT",
      "realEstateTypeName": "아파트",
      "detailAddress": "377-26",
      "latitude": 37.55775,
      "longitude": 127.010985,
      "totalHouseholdCount": 12,
      "totalBuildingCount": 1,
      "highFloor": 7,
      "lowFloor": 7,
      "useApproveYmd": "20001206",
      "dealCount": 0,
      "leaseCount": 0,
      "rentCount": 0,
      "shortTermRentCount": 0,
      "cortarAddress": "서울시 중구 신당동",
      "tourExist": false
    },
    {
      "complexNo": "137442",
      "complexName": "약수역더시티(도시형)",
      "cortarNo": "1114016200",
      "realEstateTypeCode": "APT",
      "realEstateTypeName": "아파트",
      "detailAddress": "857",
      "latitude": 37.553099,
      "longitude": 127.010759,
      "totalHouseholdCount": 153,
      "totalBuildingCount": 1,
      "highFloor": 11,
      "lowFloor": 11,
      "useApproveYmd": "20210326",
      "dealCount": 21,
      "leaseCount": 2,
      "rentCount": 2,
      "shortTermRentCount": 0,
      "cortarAddress": "서울시 중구 신당동",
      "tourExist": false
    },
    {
      "complexNo": "138286",
      "complexName": "약수일번",
      "cortarNo": "1114016200",
      "realEstateTypeCode": "APT",
      "realEstateTypeName": "아파트",
      "detailAddress": "420-1",
      "latitude": 37.556955,
      "longitude": 127.009958,
      "totalHouseholdCount": 7,
      "totalBuildingCount": 1,
      "highFloor": 6,
      "lowFloor": 4,
      "useApproveYmd": "20150115",
      "dealCount": 0,
      "leaseCount": 0,
      "rentCount": 0,
      "shortTermRentCount": 0,
      "cortarAddress": "서울시 중구 신당동",
      "tourExist": false
    },
    {
      "complexNo": "1238",
      "complexName": "약수하이츠",
      "cortarNo": "1114016200",
      "realEstateTypeCode": "APT",
      "realEstateTypeName": "아파트",
      "detailAddress": "842",
      "latitude": 37.554916,
      "longitude": 127.01478,
      "totalHouseholdCount": 2282,
      "totalBuildingCount": 19,
      "highFloor": 20,
      "lowFloor": 8,
      "useApproveYmd": "19990729",
      "dealCount": 21,
      "leaseCount": 4,
      "rentCount": 0,
      "shortTermRentCount": 0,
      "cortarAddress": "서울시 중구 신당동",
      "tourExist": false
    },
    {
      "complexNo": "137483",
      "complexName": "엘바움(도시형)",
      "cortarNo": "1114016200",
      "realEstateTypeCode": "APT",
      "realEstateTypeName": "아파트",
      "detailAddress": "251-73",
      "latitude": 37.566222,
      "longitude": 127.013649,
      "totalHouseholdCount": 24,
      "totalBuildingCount": 1,
      "highFloor": 10,
      "lowFloor": 10,
      "useApproveYmd": "20201103",
      "dealCount": 0,
      "leaseCount": 0,
      "rentCount": 0,
      "shortTermRentCount": 0,
      "cortarAddress": "서울시 중구 신당동",
      "tourExist": false
    },
    {
      "complexNo": "156123",
      "complexName": "자강헌(주상복합)",
      "cortarNo": "1114016200",
      "realEstateTypeCode": "APT",
      "realEstateTypeName": "아파트",
      "detailAddress": "367-12",
      "latitude": 37.553218,
      "longitude": 127.010535,
      "totalHouseholdCount": 11,
      "totalBuildingCount": 1,
      "highFloor": 8,
      "lowFloor": 5,
      "useApproveYmd": "20210422",
      "dealCount": 0,
      "leaseCount": 0,
      "rentCount": 0,
      "shortTermRentCount": 0,
      "cortarAddress": "서울시 중구 신당동",
      "tourExist": false
    },
    {
      "complexNo": "146430",
      "complexName": "장충아이빌2",
      "cortarNo": "1114016200",
      "realEstateTypeCode": "APT",
      "realEstateTypeName": "아파트",
      "detailAddress": "420-16",
      "latitude": 37.556944,
      "longitude": 127.010043,
      "totalHouseholdCount": 8,
      "totalBuildingCount": 1,
      "highFloor": 6,
      "lowFloor": 4,
      "useApproveYmd": "20151217",
      "dealCount": 0,
      "leaseCount": 0,
      "rentCount": 0,
      "shortTermRentCount": 0,
      "cortarAddress": "서울시 중구 신당동",
      "tourExist": false
    },
    {
      "complexNo": "26546",
      "complexName": "진달래",
      "cortarNo": "1114016200",
      "realEstateTypeCode": "APT",
      "realEstateTypeName": "아파트",
      "detailAddress": "333-42",
      "latitude": 37.55655,
      "longitude": 127.01406,
      "totalHouseholdCount": 19,
      "totalBuildingCount": 1,
      "highFloor": 5,
      "lowFloor": 4,
      "useApproveYmd": "20030923",
      "dealCount": 2,
      "leaseCount": 0,
      "rentCount": 0,
      "shortTermRentCount": 0,
      "cortarAddress": "서울시 중구 신당동",
      "tourExist": false
    },
    {
      "complexNo": "8619",
      "complexName": "청구",
      "cortarNo": "1114016200",
      "realEstateTypeCode": "APT",
      "realEstateTypeName": "아파트",
      "detailAddress": "841-14",
      "latitude": 37.557658,
      "longitude": 127.016204,
      "totalHouseholdCount": 72,
      "totalBuildingCount": 10,
      "highFloor": 5,
      "lowFloor": 5,
      "useApproveYmd": "20000501",
      "dealCount": 1,
      "leaseCount": 0,
      "rentCount": 2,
      "shortTermRentCount": 0,
      "cortarAddress": "서울시 중구 신당동",
      "tourExist": false
    },
    {
      "complexNo": "100310",
      "complexName": "청구e편한세상",
      "cortarNo": "1114016200",
      "realEstateTypeCode": "APT",
      "realEstateTypeName": "아파트",
      "detailAddress": "852",
      "latitude": 37.560569,
      "longitude": 127.016558,
      "totalHouseholdCount": 895,
      "totalBuildingCount": 15,
      "highFloor": 15,
      "lowFloor": 7,
      "useApproveYmd": "20111215",
      "dealCount": 12,
      "leaseCount": 2,
      "rentCount": 0,
      "shortTermRentCount": 0,
      "cortarAddress": "서울시 중구 신당동",
      "tourExist": false
    },
    {
      "complexNo": "26959",
      "complexName": "청구드림",
      "cortarNo": "1114016200",
      "realEstateTypeCode": "APT",
      "realEstateTypeName": "아파트",
      "detailAddress": "290-90",
      "latitude": 37.561024,
      "longitude": 127.015696,
      "totalHouseholdCount": 19,
      "totalBuildingCount": 1,
      "highFloor": 7,
      "lowFloor": 7,
      "useApproveYmd": "20020321",
      "dealCount": 4,
      "leaseCount": 0,
      "rentCount": 0,
      "shortTermRentCount": 0,
      "cortarAddress": "서울시 중구 신당동",
      "tourExist": false
    },
    {
      "complexNo": "26795",
      "complexName": "청구파크뷰",
      "cortarNo": "1114016200",
      "realEstateTypeCode": "APT",
      "realEstateTypeName": "아파트",
      "detailAddress": "292-35",
      "latitude": 37.5622,
      "longitude": 127.01582,
      "totalHouseholdCount": 19,
      "totalBuildingCount": 1,
      "highFloor": 7,
      "lowFloor": 5,
      "useApproveYmd": "20030801",
      "dealCount": 3,
      "leaseCount": 0,
      "rentCount": 0,
      "shortTermRentCount": 0,
      "cortarAddress": "서울시 중구 신당동",
      "tourExist": false
    },
    {
      "complexNo": "16729",
      "complexName": "타워",
      "cortarNo": "1114016200",
      "realEstateTypeCode": "APT",
      "realEstateTypeName": "아파트",
      "detailAddress": "294-12",
      "latitude": 37.56025,
      "longitude": 127.01468,
      "totalHouseholdCount": 12,
      "totalBuildingCount": 1,
      "highFloor": 7,
      "lowFloor": 7,
      "useApproveYmd": "20021007",
      "dealCount": 0,
      "leaseCount": 0,
      "rentCount": 0,
      "shortTermRentCount": 0,
      "cortarAddress": "서울시 중구 신당동",
      "tourExist": false
    },
    {
      "complexNo": "122768",
      "complexName": "태원팰리스3차",
      "cortarNo": "1114016200",
      "realEstateTypeCode": "APT",
      "realEstateTypeName": "아파트",
      "detailAddress": "413-4",
      "latitude": 37.558477,
      "longitude": 127.010589,
      "totalHouseholdCount": 13,
      "totalBuildingCount": 1,
      "highFloor": 5,
      "lowFloor": 4,
      "useApproveYmd": "20041222",
      "dealCount": 0,
      "leaseCount": 0,
      "rentCount": 0,
      "shortTermRentCount": 0,
      "cortarAddress": "서울시 중구 신당동",
      "tourExist": false
    },
    {
      "complexNo": "120708",
      "complexName": "태원팰리스5차",
      "cortarNo": "1114016200",
      "realEstateTypeCode": "APT",
      "realEstateTypeName": "아파트",
      "detailAddress": "432-1132",
      "latitude": 37.553124,
      "longitude": 127.007371,
      "totalHouseholdCount": 17,
      "totalBuildingCount": 1,
      "highFloor": 6,
      "lowFloor": 3,
      "useApproveYmd": "20060515",
      "dealCount": 1,
      "leaseCount": 0,
      "rentCount": 0,
      "shortTermRentCount": 0,
      "cortarAddress": "서울시 중구 신당동",
      "tourExist": false
    },
    {
      "complexNo": "26603",
      "complexName": "토토타워",
      "cortarNo": "1114016200",
      "realEstateTypeCode": "APT",
      "realEstateTypeName": "아파트",
      "detailAddress": "432-1061",
      "latitude": 37.550572,
      "longitude": 127.005999,
      "totalHouseholdCount": 12,
      "totalBuildingCount": 1,
      "highFloor": 5,
      "lowFloor": 5,
      "useApproveYmd": "20010712",
      "dealCount": 1,
      "leaseCount": 0,
      "rentCount": 0,
      "shortTermRentCount": 0,
      "cortarAddress": "서울시 중구 신당동",
      "tourExist": false
    },
    {
      "complexNo": "144494",
      "complexName": "트레져빌(도시형)",
      "cortarNo": "1114016200",
      "realEstateTypeCode": "APT",
      "realEstateTypeName": "아파트",
      "detailAddress": "432-1655",
      "latitude": 37.549498,
      "longitude": 127.005529,
      "totalHouseholdCount": 19,
      "totalBuildingCount": 1,
      "highFloor": 5,
      "lowFloor": 5,
      "useApproveYmd": "20171201",
      "dealCount": 0,
      "leaseCount": 0,
      "rentCount": 0,
      "shortTermRentCount": 0,
      "cortarAddress": "서울시 중구 신당동",
      "tourExist": false
    },
    {
      "complexNo": "124871",
      "complexName": "푸른마을(166-1)",
      "cortarNo": "1114016200",
      "realEstateTypeCode": "APT",
      "realEstateTypeName": "아파트",
      "detailAddress": "166-1",
      "latitude": 37.562967,
      "longitude": 127.023043,
      "totalHouseholdCount": 10,
      "totalBuildingCount": 1,
      "highFloor": 6,
      "lowFloor": 6,
      "useApproveYmd": "20030314",
      "dealCount": 0,
      "leaseCount": 0,
      "rentCount": 0,
      "shortTermRentCount": 0,
      "cortarAddress": "서울시 중구 신당동",
      "tourExist": false
    },
    {
      "complexNo": "8924",
      "complexName": "푸른마을(432-921)",
      "cortarNo": "1114016200",
      "realEstateTypeCode": "APT",
      "realEstateTypeName": "아파트",
      "detailAddress": "432-921",
      "latitude": 37.550814,
      "longitude": 127.005837,
      "totalHouseholdCount": 47,
      "totalBuildingCount": 3,
      "highFloor": 5,
      "lowFloor": 4,
      "useApproveYmd": "20000819",
      "dealCount": 0,
      "leaseCount": 0,
      "rentCount": 0,
      "shortTermRentCount": 0,
      "cortarAddress": "서울시 중구 신당동",
      "tourExist": false
    },
    {
      "complexNo": "26960",
      "complexName": "하이(113-5)",
      "cortarNo": "1114016200",
      "realEstateTypeCode": "APT",
      "realEstateTypeName": "아파트",
      "detailAddress": "113-5",
      "latitude": 37.5642,
      "longitude": 127.01768,
      "totalHouseholdCount": 18,
      "totalBuildingCount": 1,
      "highFloor": 6,
      "lowFloor": 5,
      "useApproveYmd": "20001101",
      "dealCount": 2,
      "leaseCount": 0,
      "rentCount": 0,
      "shortTermRentCount": 0,
      "cortarAddress": "서울시 중구 신당동",
      "tourExist": false
    },
    {
      "complexNo": "108051",
      "complexName": "하이(113-7)",
      "cortarNo": "1114016200",
      "realEstateTypeCode": "APT",
      "realEstateTypeName": "아파트",
      "detailAddress": "113-7",
      "latitude": 37.563976,
      "longitude": 127.017423,
      "totalHouseholdCount": 19,
      "totalBuildingCount": 1,
      "highFloor": 6,
      "lowFloor": 5,
      "useApproveYmd": "20010629",
      "dealCount": 0,
      "leaseCount": 0,
      "rentCount": 0,
      "shortTermRentCount": 0,
      "cortarAddress": "서울시 중구 신당동",
      "tourExist": false
    },
    {
      "complexNo": "118192",
      "complexName": "한스(도시형)",
      "cortarNo": "1114016200",
      "realEstateTypeCode": "APT",
      "realEstateTypeName": "아파트",
      "detailAddress": "340-127",
      "latitude": 37.555996,
      "longitude": 127.012468,
      "totalHouseholdCount": 45,
      "totalBuildingCount": 1,
      "highFloor": 10,
      "lowFloor": 10,
      "useApproveYmd": "20111201",
      "dealCount": 0,
      "leaseCount": 2,
      "rentCount": 0,
      "shortTermRentCount": 0,
      "cortarAddress": "서울시 중구 신당동",
      "tourExist": false
    },
    {
      "complexNo": "797",
      "complexName": "현대",
      "cortarNo": "1114016200",
      "realEstateTypeCode": "APT",
      "realEstateTypeName": "아파트",
      "detailAddress": "840",
      "latitude": 37.560164,
      "longitude": 127.021751,
      "totalHouseholdCount": 942,
      "totalBuildingCount": 10,
      "highFloor": 15,
      "lowFloor": 12,
      "useApproveYmd": "19930917",
      "dealCount": 36,
      "leaseCount": 7,
      "rentCount": 4,
      "shortTermRentCount": 0,
      "cortarAddress": "서울시 중구 신당동",
      "tourExist": false
    }
  ]
}