{
  "complexList": [
    {
      "complexNo": "701",
      "complexName": "국화맨션",
      "cortarNo": "1156012100",
      "realEstateTypeCode": "JGC",
      "realEstateTypeName": "재건축",
      "detailAddress": "76-1",
      "latitude": 37.516379,
      "longitude": 126.892766,
      "totalHouseholdCount": 270,
      "totalBuildingCount": 2,
      "highFloor": 15,
      "lowFloor": 15,
      "useApproveYmd": "19831219",
      "dealCount": 7,
      "leaseCount": 0,
      "rentCount": 0,
      "shortTermRentCount": 0,
      "cortarAddress": "서울시 영등포구 문래동3가",
      "tourExist": false
    },
    {
      "complexNo": "138447",
      "complexName": "디아인스",
      "cortarNo": "1156012100",
      "realEstateTypeCode": "APT",
      "realEstateTypeName": "아파트",
      "detailAddress": "82-10",
      "latitude": 37.520178,
      "longitude": 126.891729,
      "totalHouseholdCount": 14,
      "totalBuildingCount": 1,
      "highFloor": 8,
      "lowFloor": 7,
      "useApproveYmd": "20160406",
      "dealCount": 0,
      "leaseCount": 0,
      "rentCount": 0,
      "shortTermRentCount": 0,
      "cortarAddress": "서울시 영등포구 문래동3가",
      "tourExist": false
    },
    {
      "complexNo": "889",
      "complexName": "문래건영",
      "cortarNo": "1156012100",
      "realEstateTypeCode": "APT",
      "realEstateTypeName": "아파트",
      "detailAddress": "93-1",
      "latitude": 37.51838,
      "longitude": 126.89234,
      "totalHouseholdCount": 141,
      "totalBuildingCount": 1,
      "highFloor": 16,
      "lowFloor": 9,
      "useApproveYmd": "19980406",
      "dealCount": 8,
      "leaseCount": 0,
      "rentCount": 0,
      "shortTermRentCount": 0,
      "cortarAddress": "서울시 영등포구 문래동3가",
      "tourExist": false
    },
    {
      "complexNo": "700",
      "complexName": "문래공원한신",
      "cortarNo": "1156012100",
      "realEstateTypeCode": "APT",
      "realEstateTypeName": "아파트",
      "detailAddress": "77-2",
      "latitude": 37.517623,
      "longitude": 126.892851,
      "totalHouseholdCount": 367,
      "totalBuildingCount": 2,
      "highFloor": 15,
      "lowFloor": 13,
      "useApproveYmd": "19880719",
      "dealCount": 8,
      "leaseCount": 4,
      "rentCount": 1,
      "shortTermRentCount": 0,
      "cortarAddress": "서울시 영등포구 문래동3가",
      "tourExist": false
    },
    {
      "complexNo": "22328",
      "complexName": "문래금호어울림",
      "cortarNo": "1156012100",
      "realEstateTypeCode": "APT",
      "realEstateTypeName": "아파트",
      "detailAddress": "97",
      "latitude": 37.519256,
      "longitude": 126.897861,
      "totalHouseholdCount": 134,
      "totalBuildingCount": 3,
      "highFloor": 15,
      "lowFloor": 14,
      "useApproveYmd": "20060929",
      "dealCount": 6,
      "leaseCount": 0,
      "rentCount": 0,
      "shortTermRentCount": 0,
      "cortarAddress": "서울시 영등포구 문래동3가",
      "tourExist": false
    },
    {
      "complexNo": "21410",
      "complexName": "문래동원데자뷰",
      "cortarNo": "1156012100",
      "realEstateTypeCode": "APT",
      "realEstateTypeName": "아파트",
      "detailAddress": "95",
      "latitude": 37.517254,
      "longitude": 126.891952,
      "totalHouseholdCount": 54,
      "totalBuildingCount": 1,
      "highFloor": 13,
      "lowFloor": 7,
      "useApproveYmd": "20041230",
      "dealCount": 3,
      "leaseCount": 0,
      "rentCount": 0,
      "shortTermRentCount": 0,
      "cortarAddress": "서울시 영등포구 문래동3가",
      "tourExist": false
    },
    {
      "complexNo": "1212",
      "complexName": "문래우정",
      "cortarNo": "1156012100",
      "realEstateTypeCode": "APT",
      "realEstateTypeName": "아파트",
      "detailAddress": "78",
      "latitude": 37.515595,
      "longitude": 126.892802,
      "totalHouseholdCount": 103,
      "totalBuildingCount": 1,
      "highFloor": 15,
      "lowFloor": 9,
      "useApproveYmd": "19981208",
      "dealCount": 7,
      "leaseCount": 1,
      "rentCount": 1,
      "shortTermRentCount": 0,
      "cortarAddress": "서울시 영등포구 문래동3가",
      "tourExist": false
    },
    {
      "complexNo": "3452",
      "complexName": "문래자이",
      "cortarNo": "1156012100",
      "realEstateTypeCode": "APT",
      "realEstateTypeName": "아파트",
      "detailAddress": "54",
      "latitude": 37.516408,
      "longitude": 126.896862,
      "totalHouseholdCount": 1302,
      "totalBuildingCount": 18,
      "highFloor": 25,
      "lowFloor": 20,
      "useApproveYmd": "20011121",
      "dealCount": 18,
      "leaseCount": 1,
      "rentCount": 2,
      "shortTermRentCount": 0,
      "cortarAddress": "서울시 영등포구 문래동3가",
      "tourExist": false
    },
    {
      "complexNo": "17268",
      "complexName": "문래태영데시앙",
      "cortarNo": "1156012100",
      "realEstateTypeCode": "APT",
      "realEstateTypeName": "아파트",
      "detailAddress": "96",
      "latitude": 37.519601,
      "longitude": 126.897177,
      "totalHouseholdCount": 68,
      "totalBuildingCount": 1,
      "highFloor": 15,
      "lowFloor": 13,
      "useApproveYmd": "20050825",
      "dealCount": 5,
      "leaseCount": 0,
      "rentCount": 0,
      "shortTermRentCount": 0,
      "cortarAddress": "서울시 영등포구 문래동3가",
      "tourExist": false
    },
    {
      "complexNo": "1213",
      "complexName": "문래해태",
      "cortarNo": "1156012100",
      "realEstateTypeCode": "APT",
      "realEstateTypeName": "아파트",
      "detailAddress": "13",
      "latitude": 37.517225,
      "longitude": 126.901318,
      "totalHouseholdCount": 101,
      "totalBuildingCount": 2,
      "highFloor": 21,
      "lowFloor": 11,
      "useApproveYmd": "19990909",
      "dealCount": 6,
      "leaseCount": 2,
      "rentCount": 2,
      "shortTermRentCount": 0,
      "cortarAddress": "서울시 영등포구 문래동3가",
      "tourExist": false
    },
    {
      "complexNo": "3450",
      "complexName": "문래힐스테이트",
      "cortarNo": "1156012100",
      "realEstateTypeCode": "APT",
      "realEstateTypeName": "아파트",
      "detailAddress": "94",
      "latitude": 37.518745,
      "longitude": 126.890482,
      "totalHouseholdCount": 776,
      "totalBuildingCount": 14,
      "highFloor": 24,
      "lowFloor": 14,
      "useApproveYmd": "20030619",
      "dealCount": 23,
      "leaseCount": 3,
      "rentCount": 2,
      "shortTermRentCount": 0,
      "cortarAddress": "서울시 영등포구 문래동3가",
      "tourExist": false
    },
    {
      "complexNo": "133027",
      "complexName": "세종에버그린",
      "cortarNo": "1156012100",
      "realEstateTypeCode": "APT",
      "realEstateTypeName": "아파트",
      "detailAddress": "81",
      "latitude": 37.520477,
      "longitude": 126.892076,
      "totalHouseholdCount": 29,
      "totalBuildingCount": 2,
      "highFloor": 8,
      "lowFloor": 7,
      "useApproveYmd": "20170118",
      "dealCount": 0,
      "leaseCount": 0,
      "rentCount": 0,
      "shortTermRentCount": 0,
      "cortarAddress": "서울시 영등포구 문래동3가",
      "tourExist": false
    },
    {
      "complexNo": "113607",
      "complexName": "예지팰리스77차",
      "cortarNo": "1156012100",
      "realEstateTypeCode": "APT",
      "realEstateTypeName": "아파트",
      "detailAddress": "99",
      "latitude": 37.520202,
      "longitude": 126.892044,
      "totalHouseholdCount": 49,
      "totalBuildingCount": 1,
      "highFloor": 11,
      "lowFloor": 10,
      "useApproveYmd": "20150925",
      "dealCount": 3,
      "leaseCount": 1,
      "rentCount": 0,
      "shortTermRentCount": 0,
      "cortarAddress": "서울시 영등포구 문래동3가",
      "tourExist": false
    }
  ]
}